FinanceTrackerCLI/__init__.py
FinanceTrackerCLI/finance_tracker.py
FinanceTrackerCLI/logic/__init__.py
FinanceTrackerCLI/logic/grouped_data.py
FinanceTrackerCLI/logic/input_data.py
FinanceTrackerCLI/logic/local_convertor.py
FinanceTrackerCLI/logic/search_by_month_data.py
FinanceTrackerCLI/logic/show_all_delete_string.py
FinanceTrackerCLI/logic/terminal_name.py
FinanceTrackerCLI/logic/text_prompts.py
FinanceTrackerCLI-1.4.0.dist-info/LICENSE
FinanceTrackerCLI-1.4.0.dist-info/METADATA
FinanceTrackerCLI-1.4.0.dist-info/WHEEL
FinanceTrackerCLI-1.4.0.dist-info/entry_points.txt
FinanceTrackerCLI-1.4.0.dist-info/top_level.txt
FinanceTrackerCLI-1.4.0.dist-info/RECORD
