Metadata-Version: 2.1
Name: FinanceTrackerCLI
Version: 1.4.0
Summary: Can be run in the console from anywhere.
Home-page: https://github.com/VladimirKobranov/FinanceTrackerCLI
Author: Vladimir Kobranov
Author-email: josephclturok@gmail.com
Classifier: Programming Language :: Python :: 3.11
Classifier: License :: OSI Approved :: MIT License
Classifier: Operating System :: MacOS
Requires-Python: >=3.11
License-File: LICENSE
Requires-Dist: forex-python (==1.8)
